ejercicio04/ej04.v


module Buffer_4(input wire enable, input wire [3:0]A, output wire [3:0] Y);

  assign Y = enable ? A : 4'bz;
  
endmodule

ejercicio04/ej04_tb.v

module testbench();

  reg enable;
  reg [3:0] A;
  wire[3:0] Y;

  Buffer_4 B1(enable, A, Y);

  initial begin
      $display("\nBuffer Triestado\n");
      $display(" Enable    A    |    Y    ");
      $display(" -----------------------");
      $monitor(" %b        %b  |   %b ", enable, A, Y);
      #1 enable = 0; A[0]=0; A[1]=1; A[2]=1; A[3]=0;
      #1 enable = 0; A[0]=0; A[1]=1; A[2]=0; A[3]=1;
      #1 enable = 0; A[0]=1; A[1]=1; A[2]=1; A[3]=1;
      #1 enable = 1; A[0]=1; A[1]=1; A[2]=0; A[3]=0;
      #1 enable = 0; A[0]=1; A[1]=0; A[2]=0; A[3]=0;
      #1 enable = 1; A[0]=1; A[1]=1; A[2]=1; A[3]=1;
      #1 enable = 1; A[0]=1; A[1]=0; A[2]=1; A[3]=0;
      #1 enable = 1; A[0]=1; A[1]=0; A[2]=0; A[3]=1;
      #1 $finish;

  end

  initial begin
    $dumpfile("ej04_tb.vcd");
    $dumpvars(0, testbench);
  end

endmodule

ejercicio04/ej04_tb.vcd
$date
	Sat Oct 31 01:13:10 2020
$end
$version
	Icarus Verilog
$end
$timescale
	1ps
$end
$scope module testbench $end
$var wire 4 ! Y [3:0] $end
$var reg 4 " A [3:0] $end
$var reg 1 # enable $end
$scope module B1 $end
$var wire 4 $ A [3:0] $end
$var wire 1 # enable $end
$var wire 4 % Y [3:0] $end
$upscope $end
$upscope $end
$enddefinitions $end
#0
$dumpvars
bx %
bx $
x#
bx "
bx !
$end
#1
bz !
bz %
b110 "
b110 $
0#
#2
b1010 "
b1010 $
#3
b1111 "
b1111 $
#4
b11 !
b11 %
b11 "
b11 $
1#
#5
bz !
bz %
b1 "
b1 $
0#
#6
b1111 !
b1111 %
b1111 "
b1111 $
1#
#7
b101 !
b101 %
b101 "
b101 $
#8
b1001 !
b1001 %
b1001 "
b1001 $
