ejercicio05/ej05.v

module ROM (input wire [6:0]Address, output reg [12:0]Y);//implementacion de rom por switch case
  always @(Address) begin
    case (Address)
      7'b0000000: Y = 13'b1000000001000 ;//primer caso con Don't cares
      7'b1000000: Y = 13'b1000000001000 ;
      7'b0100000: Y = 13'b1000000001000 ;
      7'b0010000: Y = 13'b1000000001000 ;
      7'b0001000: Y = 13'b1000000001000 ;
      7'b0000100: Y = 13'b1000000001000 ;
      7'b0000010: Y = 13'b1000000001000 ;
      7'b1111110: Y = 13'b1000000001000 ;
      7'b1111100: Y = 13'b1000000001000 ;
      7'b1111000: Y = 13'b1000000001000 ;
      7'b1110000: Y = 13'b1000000001000 ;
      7'b1100000: Y = 13'b1000000001000 ;
      7'b0111110: Y = 13'b1000000001000 ;
      7'b0011110: Y = 13'b1000000001000 ;
      7'b0001110: Y = 13'b1000000001000 ;
      7'b0000110: Y = 13'b1000000001000 ;
      7'b1011110: Y = 13'b1000000001000 ;
      7'b1001110: Y = 13'b1000000001000 ;
      7'b1000110: Y = 13'b1000000001000 ;
      7'b1000010: Y = 13'b1000000001000 ;
      7'b1101110: Y = 13'b1000000001000 ;
      7'b1100110: Y = 13'b1000000001000 ;
      7'b1100010: Y = 13'b1000000001000 ;
      7'b1110110: Y = 13'b1000000001000 ;
      7'b1110010: Y = 13'b1000000001000 ;
      7'b1111010: Y = 13'b1000000001000 ;
      7'b1111100: Y = 13'b1000000001000 ;//caso 1
      7'b0000101: Y = 13'b0100000001000 ;
      7'b0000111: Y = 13'b0100000001000 ;//caso 2
      7'b0000001: Y = 13'b1000000001000 ;
      7'b0000011: Y = 13'b1000000001000 ;//caso 3
      7'b0001101: Y = 13'b1000000001000 ;
      7'b0001111: Y = 13'b1000000001000 ;//caso 4
      7'b0001001: Y = 13'b0100000001000 ;
      7'b0001011: Y = 13'b0100000001000 ;//caso 5
      7'b0010001: Y = 13'b0001001000010 ;
      7'b0010011: Y = 13'b0001001000010 ;
      7'b0010101: Y = 13'b0001001000010 ;
      7'b0010111: Y = 13'b0001001000010 ;//caso 6
      7'b0011001: Y = 13'b1001001100000 ;
      7'b0011011: Y = 13'b1001001100000 ;
      7'b0011101: Y = 13'b1001001100000 ;
      7'b0011111: Y = 13'b1001001100000 ;//caso 7
      7'b0100001: Y = 13'b0011010000010 ;
      7'b0100011: Y = 13'b0011010000010 ;
      7'b0100101: Y = 13'b0011010000010 ;
      7'b0100111: Y = 13'b0011010000010 ;//caso8
      7'b0101001: Y = 13'b0011010000100 ;
      7'b0101011: Y = 13'b0011010000100 ;
      7'b0101101: Y = 13'b0011010000100 ;
      7'b0101111: Y = 13'b0011010000100 ;//Caso 9
      7'b0110001: Y = 13'b1011010100000 ;
      7'b0110011: Y = 13'b1011010100000 ;
      7'b0110101: Y = 13'b1011010100000 ;
      7'b0110111: Y = 13'b1011010100000 ;//caso 10
      7'b0111001: Y = 13'b1000000111000 ;
      7'b0111011: Y = 13'b1000000111000 ;
      7'b0111101: Y = 13'b1000000111000 ;
      7'b0111111: Y = 13'b1000000111000 ;//caso 11
      7'b1000011: Y = 13'b0100000001000 ;
      7'b1000111: Y = 13'b0100000001000 ;//caso 12
      7'b1000001: Y = 13'b1000000001000 ;
      7'b1000101: Y = 13'b1000000001000 ;//caso 13
      7'b1001011: Y = 13'b1000000001000 ;
      7'b1001111: Y = 13'b1000000001000 ;//caso 14
      7'b1001001: Y = 13'b0100000001000 ;
      7'b1001101: Y = 13'b0100000001000 ;//caso 15
      7'b1010001: Y = 13'b0011011000010 ;
      7'b1010011: Y = 13'b0011011000010 ;
      7'b1010101: Y = 13'b0011011000010 ;
      7'b1010111: Y = 13'b0011011000010 ;//caso 16
      7'b1011001: Y = 13'b1011011100000 ;
      7'b1011011: Y = 13'b1011011100000 ;
      7'b1011101: Y = 13'b1011011100000 ;
      7'b1011111: Y = 13'b1011011100000 ;//caso 17
      7'b1100001: Y = 13'b0100000001000 ;
      7'b1100011: Y = 13'b0100000001000 ;
      7'b1100101: Y = 13'b0100000001000 ;
      7'b1100111: Y = 13'b0100000001000 ;//caso 18
      7'b1101001: Y = 13'b0000000001001 ;
      7'b1101011: Y = 13'b0000000001001 ;
      7'b1101101: Y = 13'b0000000001001 ;
      7'b1101111: Y = 13'b0000000001001 ;//caso 19
      7'b1110001: Y = 13'b0011100000010 ;
      7'b1110011: Y = 13'b0011100000010 ;
      7'b1110101: Y = 13'b0011100000010 ;
      7'b1110111: Y = 13'b0011100000010 ;//caso 20
      7'b1111001: Y = 13'b1011100100000 ;
      7'b1111011: Y = 13'b1011100100000 ;
      7'b1111101: Y = 13'b1011100100000 ;
      7'b1111111: Y = 13'b1011100100000 ;//caso 21
      default:    Y = 13'bxxxxxxxxxxxxx ; // caso por default
    endcase
  end

endmodule

ejercicio05/ej05_tb.v

module testbench ();
reg [6:0]ADDRESS;
wire [12:0]Y;

ROM Mem1(ADDRESS,Y);

initial begin
#1
$display("\n");
$display(" MEMORIA ROM ");
$display("ADDRESS \t |  Y");
$monitor("%b \t | %b ", ADDRESS, Y );
#1 ADDRESS = 7'b0000000;//caso1
#1 ADDRESS = 7'b0100000;//caso 1
#1 ADDRESS = 7'b1000000;//caso 1
#1 ADDRESS = 7'b0000010;//caso 1
#1 ADDRESS = 7'b1111110;//caso 1
#1 ADDRESS = 7'b1111100;//caso 1  
#1 ADDRESS = 7'b0000101;//caso 2
#1 ADDRESS = 7'b0000011;//caso 3
#1 ADDRESS = 7'b0001101;//caso 4
#1 ADDRESS = 7'b0010011;//caso 6
#1 ADDRESS = 7'b0011001;//caso 7
#1 ADDRESS = 7'b0101101;//caso 9
#1 ADDRESS = 7'b0100101;//caso 8
#1 ADDRESS = 7'b0110011;//caso 10
#1 ADDRESS = 7'b0111001;//caso 11
#1 ADDRESS = 7'b1000111;//caso 12
#1 ADDRESS = 7'b1001111;//caso 14
#1 ADDRESS = 7'b0000001;//caso 13
#1 ADDRESS = 7'b1001001;//caso 15
#1 ADDRESS = 7'b1010001;//caso 16
#1 ADDRESS = 7'b1011011;//caso 17
#1 ADDRESS = 7'b1111111;//caso 21
#1 ADDRESS = 7'b1110111;//caso 20
#1 ADDRESS = 7'b1101001;//caso 19
#1 ADDRESS = 7'b1100001;//caso 18
#1 ADDRESS = 7'b0011111;//caso 7
#1 ADDRESS = 7'b0110111;//caso 10
#1 ADDRESS = 7'b0001011;//caso 5
#1 ADDRESS = 7'b1001101;//caso 15
#1 ADDRESS = 7'b1110011;//caso 20
#1 ADDRESS = 7'b1111101;//caso 21

#1 $finish;
end

initial begin
      $dumpfile("ej05_tb.vcd");
      $dumpvars(0, testbench);
    end

endmodule

ejercicio05/ej05_tb.vcd
$date
	Sat Oct 31 09:58:01 2020
$end
$version
	Icarus Verilog
$end
$timescale
	1ps
$end
$scope module testbench $end
$var wire 13 ! Y [12:0] $end
$var reg 7 " ADDRESS [6:0] $end
$scope module Mem1 $end
$var wire 7 # Address [6:0] $end
$var reg 13 $ Y [12:0] $end
$upscope $end
$upscope $end
$enddefinitions $end
#0
$dumpvars
bx $
bx #
bx "
bx !
$end
#2
b1000000001000 !
b1000000001000 $
b0 "
b0 #
#3
b100000 "
b100000 #
#4
b1000000 "
b1000000 #
#5
b10 "
b10 #
#6
b1111110 "
b1111110 #
#7
b1111100 "
b1111100 #
#8
b100000001000 !
b100000001000 $
b101 "
b101 #
#9
b1000000001000 !
b1000000001000 $
b11 "
b11 #
#10
b1101 "
b1101 #
#11
b1001000010 !
b1001000010 $
b10011 "
b10011 #
#12
b1001001100000 !
b1001001100000 $
b11001 "
b11001 #
#13
b11010000100 !
b11010000100 $
b101101 "
b101101 #
#14
b11010000010 !
b11010000010 $
b100101 "
b100101 #
#15
b1011010100000 !
b1011010100000 $
b110011 "
b110011 #
#16
b1000000111000 !
b1000000111000 $
b111001 "
b111001 #
#17
b100000001000 !
b100000001000 $
b1000111 "
b1000111 #
#18
b1000000001000 !
b1000000001000 $
b1001111 "
b1001111 #
#19
b1 "
b1 #
#20
b100000001000 !
b100000001000 $
b1001001 "
b1001001 #
#21
b11011000010 !
b11011000010 $
b1010001 "
b1010001 #
#22
b1011011100000 !
b1011011100000 $
b1011011 "
b1011011 #
#23
b1011100100000 !
b1011100100000 $
b1111111 "
b1111111 #
#24
b11100000010 !
b11100000010 $
b1110111 "
b1110111 #
#25
b1001 !
b1001 $
b1101001 "
b1101001 #
#26
b100000001000 !
b100000001000 $
b1100001 "
b1100001 #
#27
b1001001100000 !
b1001001100000 $
b11111 "
b11111 #
#28
b1011010100000 !
b1011010100000 $
b110111 "
b110111 #
#29
b100000001000 !
b100000001000 $
b1011 "
b1011 #
#30
b1001101 "
b1001101 #
#31
b11100000010 !
b11100000010 $
b1110011 "
b1110011 #
#32
b1011100100000 !
b1011100100000 $
b1111101 "
b1111101 #
