ejercicio02/ej02.v

//Flip Flop Tipo d de 1 bit
module FF_D1(input wire clk, reset, enable, D, output reg Y) ;
  always @(posedge clk or posedge enable or posedge reset) begin
    if (reset)  Y <= 1'b0;
    else if(enable) Y <= D;
  end
endmodule


//Flip Flop Tipo T de 1 bit
module FF_T(input wire clock, reset, enable, output wire Y);
  wire D;
  assign D = ~Y;
  FF_D1 G1(clock, reset, enable, D, Y);
endmodule

ejercicio02/ej02_tb.v
module testbench();

  reg clk, rst, enable;
  wire Y;

  FF_T U1(clk, rst, enable, Y);

always // instanciacion del clock
  begin
    clk <= 1;
    #1 clk <= ~clk;
    #1;
end

initial begin
    $display("\nFlip Flop Tipo T\n");
    $display(" Clk RST | EN |   Y    ");
    $display(" --------------------- ");
    $monitor(" %b    %b  |  %b |   %b ", clk, rst, enable, Y);

    #1 rst = 1; //Reset inicial
    #1 rst = 0; enable = 1; //Reset inicial
    #4 enable = 0;
    #2 enable = 1;
    #5 $finish;
end

  initial begin
        $dumpfile("ej02_tb.vcd");
        $dumpvars(0, testbench);
      end
endmodule

ejercicio02/ej02_tb.vcd
$date
	Sat Oct 31 01:05:01 2020
$end
$version
	Icarus Verilog
$end
$timescale
	1ps
$end
$scope module testbench $end
$var wire 1 ! Y $end
$var reg 1 " clk $end
$var reg 1 # enable $end
$var reg 1 $ rst $end
$scope module U1 $end
$var wire 1 % D $end
$var wire 1 " clock $end
$var wire 1 # enable $end
$var wire 1 $ reset $end
$var wire 1 ! Y $end
$scope module G1 $end
$var wire 1 % D $end
$var wire 1 " clk $end
$var wire 1 # enable $end
$var wire 1 $ reset $end
$var reg 1 ! Y $end
$upscope $end
$upscope $end
$upscope $end
$enddefinitions $end
#0
$dumpvars
x%
x$
x#
1"
x!
$end
#1
1%
0!
0"
1$
#2
0%
1!
1"
1#
0$
#3
0"
#4
1%
0!
1"
#5
0"
#6
1"
0#
#7
0"
#8
0%
1!
1"
1#
#9
0"
#10
1%
0!
1"
#11
0"
#12
0%
1!
1"
